[
    {
        "code": "25212",
        "postal_old": "52016",
        "postal_new": "5201601",
        "pref_kana": "ï½¼ï½¶ï¾ï½¹ï¾",
        "address1_kana": "ï¾€ï½¶ï½¼ï¾ï½¼",
        "address2_kana": "ï½²ï¾ï¾‚ï¾ï¾ï½®ï½³ï¾Œï½¶ï½¼ï¾ï½½ï¾",
        "pref": "æ»‹è³€çœŒ",
        "address1": "é«˜å³¶å¸‚",
        "address2": "ä»Šæ´¥ç”ºæ·±æ¸…æ°´",
        "is_multi_code": "0",
        "is_koaza": "0",
        "is_choume": "0",
        "is_multi_place": "0",
        "is_updated": "0",
        "update_reason": "0"
    },
    {
        "code": "25212",
        "postal_old": "52016",
        "postal_new": "5201602",
        "pref_kana": "ï½¼ï½¶ï¾ï½¹ï¾",
        "address1_kana": "ï¾€ï½¶ï½¼ï¾ï½¼",
        "address2_kana": "ï½²ï¾ï¾‚ï¾ï¾ï½®ï½³ï½¶ï¾‚ï¾—",
        "pref": "æ»‹è³€çœŒ",
        "address1": "é«˜å³¶å¸‚",
        "address2": "ä»Šæ´¥ç”ºæ¡‚",
        "is_multi_code": "0",
        "is_koaza": "0",
        "is_choume": "0",
        "is_multi_place": "0",
        "is_updated": "0",
        "update_reason": "0"
    },
    {
        "code": "25212",
        "postal_old": "52016",
        "postal_new": "5201603",
        "pref_kana": "ï½¼ï½¶ï¾ï½¹ï¾",
        "address1_kana": "ï¾€ï½¶ï½¼ï¾ï½¼",
        "address2_kana": "ï½²ï¾ï¾‚ï¾ï¾ï½®ï½³ï½·ï¾„ï½¹ï¾",
        "pref": "æ»‹è³€çœŒ",
        "address1": "é«˜å³¶å¸‚",
        "address2": "ä»Šæ´¥ç”ºåŒ—ä»°",
        "is_multi_code": "0",
        "is_koaza": "0",
        "is_choume": "0",
        "is_multi_place": "0",
        "is_updated": "0",
        "update_reason": "0"
    },
    {
        "code": "25212",
        "postal_old": "52016",
        "postal_new": "5201604",
        "pref_kana": "ï½¼ï½¶ï¾ï½¹ï¾",
        "address1_kana": "ï¾€ï½¶ï½¼ï¾ï½¼",
        "address2_kana": "ï½²ï¾ï¾‚ï¾ï¾ï½®ï½³ï¾Šï¾ï¾Œï¾ï¾",
        "pref": "æ»‹è³€çœŒ",
        "address1": "é«˜å³¶å¸‚",
        "address2": "ä»Šæ´¥ç”ºæµœåˆ†",
        "is_multi_code": "0",
        "is_koaza": "0",
        "is_choume": "0",
        "is_multi_place": "0",
        "is_updated": "0",
        "update_reason": "0"
    },
    {
        "code": "25212",
        "postal_old": "52016",
        "postal_new": "5201605",
        "pref_kana": "ï½¼ï½¶ï¾ï½¹ï¾",
        "address1_kana": "ï¾€ï½¶ï½¼ï¾ï½¼",
        "address2_kana": "ï½²ï¾ï¾‚ï¾ï¾ï½®ï½³ï¾ï¾…ï¾ï½¼ï¾ï¾ï¾",
        "pref": "æ»‹è³€çœŒ",
        "address1": "é«˜å³¶å¸‚",
        "address2": "ä»Šæ´¥ç”ºå—æ–°ä¿",
        "is_multi_code": "0",
        "is_koaza": "0",
        "is_choume": "0",
        "is_multi_place": "0",
        "is_updated": "0",
        "update_reason": "0"
    },
    {
        "code": "25212",
        "postal_old": "52016",
        "postal_new": "5201611",
        "pref_kana": "ï½¼ï½¶ï¾ï½¹ï¾",
        "address1_kana": "ï¾€ï½¶ï½¼ï¾ï½¼",
        "address2_kana": "ï½²ï¾ï¾‚ï¾ï¾ï½®ï½³ï¾‹ï¾›ï½¶ï¾œ",
        "pref": "æ»‹è³€çœŒ",
        "address1": "é«˜å³¶å¸‚",
        "address2": "ä»Šæ´¥ç”ºå¼˜å·",
        "is_multi_code": "0",
        "is_koaza": "0",
        "is_choume": "0",
        "is_multi_place": "0",
        "is_updated": "0",
        "update_reason": "0"
    },
    {
        "code": "25212",
        "postal_old": "52016",
        "postal_new": "5201612",
        "pref_kana": "ï½¼ï½¶ï¾ï½¹ï¾",
        "address1_kana": "ï¾€ï½¶ï½¼ï¾ï½¼",
        "address2_kana": "ï½²ï¾ï¾‚ï¾ï¾ï½®ï½³ï½¼ï¾“ï¾‹ï¾›ï¾ï¾",
        "pref": "æ»‹è³€çœŒ",
        "address1": "é«˜å³¶å¸‚",
        "address2": "ä»Šæ´¥ç”ºä¸‹å¼˜éƒ¨",
        "is_multi_code": "0",
        "is_koaza": "0",
        "is_choume": "0",
        "is_multi_place": "0",
        "is_updated": "0",
        "update_reason": "0"
    },
    {
        "code": "25212",
        "postal_old": "52016",
        "postal_new": "5201613",
        "pref_kana": "ï½¼ï½¶ï¾ï½¹ï¾",
        "address1_kana": "ï¾€ï½¶ï½¼ï¾ï½¼",
        "address2_kana": "ï½²ï¾ï¾‚ï¾ï¾ï½®ï½³ï½¶ï¾ï¾‹ï¾›ï¾ï¾",
        "pref": "æ»‹è³€çœŒ",
        "address1": "é«˜å³¶å¸‚",
        "address2": "ä»Šæ´¥ç”ºä¸Šå¼˜éƒ¨",
        "is_multi_code": "0",
        "is_koaza": "0",
        "is_choume": "0",
        "is_multi_place": "0",
        "is_updated": "0",
        "update_reason": "0"
    },
    {
        "code": "25212",
        "postal_old": "52016",
        "postal_new": "5201614",
        "pref_kana": "ï½¼ï½¶ï¾ï½¹ï¾",
        "address1_kana": "ï¾€ï½¶ï½¼ï¾ï½¼",
        "address2_kana": "ï½²ï¾ï¾‚ï¾ï¾ï½®ï½³ï¾•ï½³",
        "pref": "æ»‹è³€çœŒ",
        "address1": "é«˜å³¶å¸‚",
        "address2": "ä»Šæ´¥ç”ºè—ºç”Ÿ",
        "is_multi_code": "0",
        "is_koaza": "0",
        "is_choume": "0",
        "is_multi_place": "0",
        "is_updated": "0",
        "update_reason": "0"
    },
    {
        "code": "25212",
        "postal_old": "52016",
        "postal_new": "5201621",
        "pref_kana": "ï½¼ï½¶ï¾ï½¹ï¾",
        "address1_kana": "ï¾€ï½¶ï½¼ï¾ï½¼",
        "address2_kana": "ï½²ï¾ï¾‚ï¾ï¾ï½®ï½³ï½²ï¾ï¾‚ï¾",
        "pref": "æ»‹è³€çœŒ",
        "address1": "é«˜å³¶å¸‚",
        "address2": "ä»Šæ´¥ç”ºä»Šæ´¥",
        "is_multi_code": "0",
        "is_koaza": "0",
        "is_choume": "0",
        "is_multi_place": "0",
        "is_updated": "0",
        "update_reason": "0"
    },
    {
        "code": "25212",
        "postal_old": "52016",
        "postal_new": "5201622",
        "pref_kana": "ï½¼ï½¶ï¾ï½¹ï¾",
        "address1_kana": "ï¾€ï½¶ï½¼ï¾ï½¼",
        "address2_kana": "ï½²ï¾ï¾‚ï¾ï¾ï½®ï½³ï¾…ï½¶ï¾‡ï¾",
        "pref": "æ»‹è³€çœŒ",
        "address1": "é«˜å³¶å¸‚",
        "address2": "ä»Šæ´¥ç”ºä¸­æ²¼",
        "is_multi_code": "0",
        "is_koaza": "0",
        "is_choume": "1",
        "is_multi_place": "0",
        "is_updated": "0",
        "update_reason": "0"
    },
    {
        "code": "25212",
        "postal_old": "52016",
        "postal_new": "5201623",
        "pref_kana": "ï½¼ï½¶ï¾ï½¹ï¾",
        "address1_kana": "ï¾€ï½¶ï½¼ï¾ï½¼",
        "address2_kana": "ï½²ï¾ï¾‚ï¾ï¾ï½®ï½³ï½½ï¾ï¾–ï½¼",
        "pref": "æ»‹è³€çœŒ",
        "address1": "é«˜å³¶å¸‚",
        "address2": "ä»Šæ´¥ç”ºä½å‰",
        "is_multi_code": "0",
        "is_koaza": "0",
        "is_choume": "1",
        "is_multi_place": "0",
        "is_updated": "0",
        "update_reason": "0"
    },
    {
        "code": "25212",
        "postal_old": "52016",
        "postal_new": "5201631",
        "pref_kana": "ï½¼ï½¶ï¾ï½¹ï¾",
        "address1_kana": "ï¾€ï½¶ï½¼ï¾ï½¼",
        "address2_kana": "ï½²ï¾ï¾‚ï¾ï¾ï½®ï½³ï¾…ï½ºï½¼ï¾",
        "pref": "æ»‹è³€çœŒ",
        "address1": "é«˜å³¶å¸‚",
        "address2": "ä»Šæ´¥ç”ºåå°è·¯",
        "is_multi_code": "0",
        "is_koaza": "0",
        "is_choume": "1",
        "is_multi_place": "0",
        "is_updated": "0",
        "update_reason": "0"
    },
    {
        "code": "25212",
        "postal_old": "52016",
        "postal_new": "5201632",
        "pref_kana": "ï½¼ï½¶ï¾ï½¹ï¾",
        "address1_kana": "ï¾€ï½¶ï½¼ï¾ï½¼",
        "address2_kana": "ï½²ï¾ï¾‚ï¾ï¾ï½®ï½³ï½»ï½¸ï¾—ï¾ï¾",
        "pref": "æ»‹è³€çœŒ",
        "address1": "é«˜å³¶å¸‚",
        "address2": "ä»Šæ´¥ç”ºæ¡œç”º",
        "is_multi_code": "0",
        "is_koaza": "0",
        "is_choume": "1",
        "is_multi_place": "0",
        "is_updated": "0",
        "update_reason": "0"
    },
    {
        "code": "25212",
        "postal_old": "52016",
        "postal_new": "5201633",
        "pref_kana": "ï½¼ï½¶ï¾ï½¹ï¾",
        "address1_kana": "ï¾€ï½¶ï½¼ï¾ï½¼",
        "address2_kana": "ï½²ï¾ï¾‚ï¾ï¾ï½®ï½³ï½¼ï½®ï½³ï¾–ï½³ï¾€ï¾ï½²",
        "pref": "æ»‹è³€çœŒ",
        "address1": "é«˜å³¶å¸‚",
        "address2": "ä»Šæ´¥ç”ºæ¾é™½å°",
        "is_multi_code": "0",
        "is_koaza": "0",
        "is_choume": "1",
        "is_multi_place": "0",
        "is_updated": "0",
        "update_reason": "0"
    },
    {
        "code": "25212",
        "postal_old": "52016",
        "postal_new": "5201634",
        "pref_kana": "ï½¼ï½¶ï¾ï½¹ï¾",
        "address1_kana": "ï¾€ï½¶ï½¼ï¾ï½¼",
        "address2_kana": "ï½²ï¾ï¾‚ï¾ï¾ï½®ï½³ï½µï½µï¾„ï¾“ï¾€ï¾ï½²ï¾“ï¾",
        "pref": "æ»‹è³€çœŒ",
        "address1": "é«˜å³¶å¸‚",
        "address2": "ä»Šæ´¥ç”ºå¤§ä¾›å¤§é–€",
        "is_multi_code": "0",
        "is_koaza": "0",
        "is_choume": "1",
        "is_multi_place": "0",
        "is_updated": "0",
        "update_reason": "0"
    },
    {
        "code": "25212",
        "postal_old": "52016",
        "postal_new": "5201635",
        "pref_kana": "ï½¼ï½¶ï¾ï½¹ï¾",
        "address1_kana": "ï¾€ï½¶ï½¼ï¾ï½¼",
        "address2_kana": "ï½²ï¾ï¾‚ï¾ï¾ï½®ï½³ï½µï½µï¾„ï¾“",
        "pref": "æ»‹è³€çœŒ",
        "address1": "é«˜å³¶å¸‚",
        "address2": "ä»Šæ´¥ç”ºå¤§ä¾›",
        "is_multi_code": "0",
        "is_koaza": "0",
        "is_choume": "0",
        "is_multi_place": "0",
        "is_updated": "0",
        "update_reason": "0"
    },
    {
        "code": "25212",
        "postal_old": "52016",
        "postal_new": "5201636",
        "pref_kana": "ï½¼ï½¶ï¾ï½¹ï¾",
        "address1_kana": "ï¾€ï½¶ï½¼ï¾ï½¼",
        "address2_kana": "ï½²ï¾ï¾‚ï¾ï¾ï½®ï½³ï¾Œï¾…ï¾Šï¾ï½¼",
        "pref": "æ»‹è³€çœŒ",
        "address1": "é«˜å³¶å¸‚",
        "address2": "ä»Šæ´¥ç”ºèˆŸæ©‹",
        "is_multi_code": "0",
        "is_koaza": "0",
        "is_choume": "1",
        "is_multi_place": "0",
        "is_updated": "0",
        "update_reason": "0"
    },
    {
        "code": "25212",
        "postal_old": "52016",
        "postal_new": "5201641",
        "pref_kana": "ï½¼ï½¶ï¾ï½¹ï¾",
        "address1_kana": "ï¾€ï½¶ï½¼ï¾ï½¼",
        "address2_kana": "ï½²ï¾ï¾‚ï¾ï¾ï½®ï½³ï¾ï¾…ï¾ï½³ï¾",
        "pref": "æ»‹è³€çœŒ",
        "address1": "é«˜å³¶å¸‚",
        "address2": "ä»Šæ´¥ç”ºå—ç”Ÿè¦‹",
        "is_multi_code": "0",
        "is_koaza": "0",
        "is_choume": "0",
        "is_multi_place": "0",
        "is_updated": "0",
        "update_reason": "0"
    },
    {
        "code": "25212",
        "postal_old": "52016",
        "postal_new": "5201642",
        "pref_kana": "ï½¼ï½¶ï¾ï½¹ï¾",
        "address1_kana": "ï¾€ï½¶ï½¼ï¾ï½¼",
        "address2_kana": "ï½²ï¾ï¾‚ï¾ï¾ï½®ï½³ï½·ï¾€ï½³ï¾",
        "pref": "æ»‹è³€çœŒ",
        "address1": "é«˜å³¶å¸‚",
        "address2": "ä»Šæ´¥ç”ºåŒ—ç”Ÿè¦‹",
        "is_multi_code": "0",
        "is_koaza": "0",
        "is_choume": "0",
        "is_multi_place": "0",
        "is_updated": "0",
        "update_reason": "0"
    },
    {
        "code": "25212",
        "postal_old": "52016",
        "postal_new": "5201643",
        "pref_kana": "ï½¼ï½¶ï¾ï½¹ï¾",
        "address1_kana": "ï¾€ï½¶ï½¼ï¾ï½¼",
        "address2_kana": "ï½²ï¾ï¾‚ï¾ï¾ï½®ï½³ï¾ï½³ï½»ï¾ï½¶",
        "pref": "æ»‹è³€çœŒ",
        "address1": "é«˜å³¶å¸‚",
        "address2": "ä»Šæ´¥ç”ºä¿å‚",
        "is_multi_code": "0",
        "is_koaza": "0",
        "is_choume": "0",
        "is_multi_place": "0",
        "is_updated": "0",
        "update_reason": "0"
    },
    {
        "code": "25212",
        "postal_old": "52016",
        "postal_new": "5201644",
        "pref_kana": "ï½¼ï½¶ï¾ï½¹ï¾",
        "address1_kana": "ï¾€ï½¶ï½¼ï¾ï½¼",
        "address2_kana": "ï½²ï¾ï¾‚ï¾ï¾ï½®ï½³ï¾„ï¾ï½­ï½³ï¾€ï¾ï¾†",
        "pref": "æ»‹è³€çœŒ",
        "address1": "é«˜å³¶å¸‚",
        "address2": "ä»Šæ´¥ç”ºé€”ä¸­è°·",
        "is_multi_code": "0",
        "is_koaza": "0",
        "is_choume": "0",
        "is_multi_place": "0",
        "is_updated": "0",
        "update_reason": "0"
    },
    {
        "code": "25212",
        "postal_old": "52016",
        "postal_new": "5201645",
        "pref_kana": "ï½¼ï½¶ï¾ï½¹ï¾",
        "address1_kana": "ï¾€ï½¶ï½¼ï¾ï½¼",
        "address2_kana": "ï½²ï¾ï¾‚ï¾ï¾ï½®ï½³ï¾‘ï½¸ï½¶ï¾ï¾œ",
        "pref": "æ»‹è³€çœŒ",
        "address1": "é«˜å³¶å¸‚",
        "address2": "ä»Šæ´¥ç”ºæ¤‹å·",
        "is_multi_code": "0",
        "is_koaza": "0",
        "is_choume": "0",
        "is_multi_place": "0",
        "is_updated": "0",
        "update_reason": "0"
    },
    {
        "code": "25212",
        "postal_old": "52016",
        "postal_new": "5201646",
        "pref_kana": "ï½¼ï½¶ï¾ï½¹ï¾",
        "address1_kana": "ï¾€ï½¶ï½¼ï¾ï½¼",
        "address2_kana": "ï½²ï¾ï¾‚ï¾ï¾ï½®ï½³ï½½ï½·ï¾ï¾”ï¾",
        "pref": "æ»‹è³€çœŒ",
        "address1": "é«˜å³¶å¸‚",
        "address2": "ä»Šæ´¥ç”ºæ‰å±±",
        "is_multi_code": "0",
        "is_koaza": "0",
        "is_choume": "0",
        "is_multi_place": "0",
        "is_updated": "0",
        "update_reason": "0"
    },
    {
        "code": "25212",
        "postal_old": "52016",
        "postal_new": "5201647",
        "pref_kana": "ï½¼ï½¶ï¾ï½¹ï¾",
        "address1_kana": "ï¾€ï½¶ï½¼ï¾ï½¼",
        "address2_kana": "ï½²ï¾ï¾‚ï¾ï¾ï½®ï½³ï½±ï¾ï½½ï½¶ï¾ï¾œ",
        "pref": "æ»‹è³€çœŒ",
        "address1": "é«˜å³¶å¸‚",
        "address2": "ä»Šæ´¥ç”ºå¤©å¢—å·",
        "is_multi_code": "0",
        "is_koaza": "0",
        "is_choume": "0",
        "is_multi_place": "0",
        "is_updated": "0",
        "update_reason": "0"
    },
    {
        "code": "25212",
        "postal_old": "52016",
        "postal_new": "5201648",
        "pref_kana": "ï½¼ï½¶ï¾ï½¹ï¾",
        "address1_kana": "ï¾€ï½¶ï½¼ï¾ï½¼",
        "address2_kana": "ï½²ï¾ï¾‚ï¾ï¾ï½®ï½³ï¾‚ï¾‰ï½¶ï¾ï¾œ",
        "pref": "æ»‹è³€çœŒ",
        "address1": "é«˜å³¶å¸‚",
        "address2": "ä»Šæ´¥ç”ºè§’å·",
        "is_multi_code": "0",
        "is_koaza": "0",
        "is_choume": "0",
        "is_multi_place": "0",
        "is_updated": "0",
        "update_reason": "0"
    },
    {
        "code": "25212",
        "postal_old": "52016",
        "postal_new": "5201651",
        "pref_kana": "ï½¼ï½¶ï¾ï½¹ï¾",
        "address1_kana": "ï¾€ï½¶ï½¼ï¾ï½¼",
        "address2_kana": "ï½²ï¾ï¾‚ï¾ï¾ï½®ï½³ï½»ï¾…ï¾",
        "pref": "æ»‹è³€çœŒ",
        "address1": "é«˜å³¶å¸‚",
        "address2": "ä»Šæ´¥ç”ºé…’æ³¢",
        "is_multi_code": "0",
        "is_koaza": "0",
        "is_choume": "0",
        "is_multi_place": "0",
        "is_updated": "0",
        "update_reason": "0"
    },
    {
        "code": "25212",
        "postal_old": "52016",
        "postal_new": "5201652",
        "pref_kana": "ï½¼ï½¶ï¾ï½¹ï¾",
        "address1_kana": "ï¾€ï½¶ï½¼ï¾ï½¼",
        "address2_kana": "ï½²ï¾ï¾‚ï¾ï¾ï½®ï½³ï¾Œï½¸ï½µï½¶",
        "pref": "æ»‹è³€çœŒ",
        "address1": "é«˜å³¶å¸‚",
        "address2": "ä»Šæ´¥ç”ºç¦å²¡",
        "is_multi_code": "0",
        "is_koaza": "0",
        "is_choume": "0",
        "is_multi_place": "0",
        "is_updated": "0",
        "update_reason": "0"
    },
    {
        "code": "25212",
        "postal_old": "52016",
        "postal_new": "5201653",
        "pref_kana": "ï½¼ï½¶ï¾ï½¹ï¾",
        "address1_kana": "ï¾€ï",
        "address2_kana": null,
        "pref": null,
        "address1": null,
        "address2": null,
        "is_multi_code": null,
        "is_koaza": null,
        "is_choume": null,
        "is_multi_place": null,
        "is_updated": null,
        "update_reason": null
    }
]