[
    {
        "local_government_code": "05201",
        "postal_code_5digit": "01016",
        "postal_code_7digit": "0101601",
        "prefecture_kana": "ｱｷﾀｹﾝ",
        "address1_kana": "ｱｷﾀｼ",
        "address2_kana": "ﾑｶｲﾊﾏ",
        "prefecture_kanji": "秋田県",
        "address1_kanji": "秋田市",
        "address2_kanji": "向浜",
        "is_address2_has_multiple_postal_code": "0",
        "is_address2_has_multiple_sublocality": "0",
        "is_address2_includes_chome": "1",
        "is_postal_code_has_multiple_address2": "0",
        "updated_type": "0",
        "updated_reason_type": "0"
    },
    {
        "local_government_code": "05201",
        "postal_code_5digit": "01016",
        "postal_code_7digit": "0101602",
        "prefecture_kana": "ｱｷﾀｹﾝ",
        "address1_kana": "ｱｷﾀｼ",
        "address2_kana": "ｱﾗﾔｼﾀｶﾜﾗﾏﾁ",
        "prefecture_kanji": "秋田県",
        "address1_kanji": "秋田市",
        "address2_kanji": "新屋下川原町",
        "is_address2_has_multiple_postal_code": "0",
        "is_address2_has_multiple_sublocality": "0",
        "is_address2_includes_chome": "0",
        "is_postal_code_has_multiple_address2": "0",
        "updated_type": "0",
        "updated_reason_type": "0"
    },
    {
        "local_government_code": "05201",
        "postal_code_5digit": "01016",
        "postal_code_7digit": "0101603",
        "prefecture_kana": "ｱｷﾀｹﾝ",
        "address1_kana": "ｱｷﾀｼ",
        "address2_kana": "ｱﾗﾔｶﾂﾋﾗﾀﾞｲ",
        "prefecture_kanji": "秋田県",
        "address1_kanji": "秋田市",
        "address2_kanji": "新屋勝平台",
        "is_address2_has_multiple_postal_code": "0",
        "is_address2_has_multiple_sublocality": "0",
        "is_address2_includes_chome": "0",
        "is_postal_code_has_multiple_address2": "0",
        "updated_type": "0",
        "updated_reason_type": "0"
    },
    {
        "local_government_code": "05201",
        "postal_code_5digit": "01016",
        "postal_code_7digit": "0101604",
        "prefecture_kana": "ｱｷﾀｹﾝ",
        "address1_kana": "ｱｷﾀｼ",
        "address2_kana": "ｱﾗﾔﾏﾂﾐﾏﾁ",
        "prefecture_kanji": "秋田県",
        "address1_kanji": "秋田市",
        "address2_kanji": "新屋松美町",
        "is_address2_has_multiple_postal_code": "0",
        "is_address2_has_multiple_sublocality": "0",
        "is_address2_includes_chome": "0",
        "is_postal_code_has_multiple_address2": "0",
        "updated_type": "0",
        "updated_reason_type": "0"
    },
    {
        "local_government_code": "05201",
        "postal_code_5digit": "01016",
        "postal_code_7digit": "0101605",
        "prefecture_kana": "ｱｷﾀｹﾝ",
        "address1_kana": "ｱｷﾀｼ",
        "address2_kana": "ｱﾗﾔｶﾂﾋﾗﾏﾁ",
        "prefecture_kanji": "秋田県",
        "address1_kanji": "秋田市",
        "address2_kanji": "新屋勝平町",
        "is_address2_has_multiple_postal_code": "0",
        "is_address2_has_multiple_sublocality": "0",
        "is_address2_includes_chome": "0",
        "is_postal_code_has_multiple_address2": "0",
        "updated_type": "0",
        "updated_reason_type": "0"
    },
    {
        "local_government_code": "05201",
        "postal_code_5digit": "01016",
        "postal_code_7digit": "0101606",
        "prefecture_kana": "ｱｷﾀｹﾝ",
        "address1_kana": "ｱｷﾀｼ",
        "address2_kana": "ｱﾗﾔｺﾄﾌﾞｷﾏﾁ",
        "prefecture_kanji": "秋田県",
        "address1_kanji": "秋田市",
        "address2_kanji": "新屋寿町",
        "is_address2_has_multiple_postal_code": "0",
        "is_address2_has_multiple_sublocality": "0",
        "is_address2_includes_chome": "0",
        "is_postal_code_has_multiple_address2": "0",
        "updated_type": "0",
        "updated_reason_type": "0"
    },
    {
        "local_government_code": "05201",
        "postal_code_5digit": "01016",
        "postal_code_7digit": "0101607",
        "prefecture_kana": "ｱｷﾀｹﾝ",
        "address1_kana": "ｱｷﾀｼ",
        "address2_kana": "ｱﾗﾔﾐﾅﾐﾊﾏﾏﾁ",
        "prefecture_kanji": "秋田県",
        "address1_kanji": "秋田市",
        "address2_kanji": "新屋南浜町",
        "is_address2_has_multiple_postal_code": "0",
        "is_address2_has_multiple_sublocality": "0",
        "is_address2_includes_chome": "0",
        "is_postal_code_has_multiple_address2": "0",
        "updated_type": "0",
        "updated_reason_type": "0"
    },
    {
        "local_government_code": "05201",
        "postal_code_5digit": "01016",
        "postal_code_7digit": "0101608",
        "prefecture_kana": "ｱｷﾀｹﾝ",
        "address1_kana": "ｱｷﾀｼ",
        "address2_kana": "ｱﾗﾔｷﾀﾊﾏﾁｮｳ",
        "prefecture_kanji": "秋田県",
        "address1_kanji": "秋田市",
        "address2_kanji": "新屋北浜町",
        "is_address2_has_multiple_postal_code": "0",
        "is_address2_has_multiple_sublocality": "0",
        "is_address2_includes_chome": "0",
        "is_postal_code_has_multiple_address2": "0",
        "updated_type": "0",
        "updated_reason_type": "0"
    },
    {
        "local_government_code": "05201",
        "postal_code_5digit": "01016",
        "postal_code_7digit": "0101611",
        "prefecture_kana": "ｱｷﾀｹﾝ",
        "address1_kana": "ｱｷﾀｼ",
        "address2_kana": "ｱﾗﾔﾃﾝﾋﾞﾝﾉ",
        "prefecture_kanji": "秋田県",
        "address1_kanji": "秋田市",
        "address2_kanji": "新屋天秤野",
        "is_address2_has_multiple_postal_code": "0",
        "is_address2_has_multiple_sublocality": "0",
        "is_address2_includes_chome": "0",
        "is_postal_code_has_multiple_address2": "0",
        "updated_type": "0",
        "updated_reason_type": "0"
    },
    {
        "local_government_code": "05201",
        "postal_code_5digit": "01016",
        "postal_code_7digit": "0101612",
        "prefecture_kana": "ｱｷﾀｹﾝ",
        "address1_kana": "ｱｷﾀｼ",
        "address2_kana": "ｱﾗﾔﾕﾀｶﾏﾁ",
        "prefecture_kanji": "秋田県",
        "address1_kanji": "秋田市",
        "address2_kanji": "新屋豊町",
        "is_address2_has_multiple_postal_code": "0",
        "is_address2_has_multiple_sublocality": "0",
        "is_address2_includes_chome": "0",
        "is_postal_code_has_multiple_address2": "0",
        "updated_type": "0",
        "updated_reason_type": "0"
    },
    {
        "local_government_code": "05201",
        "postal_code_5digit": "01016",
        "postal_code_7digit": "0101613",
        "prefecture_kana": "ｱｷﾀｹﾝ",
        "address1_kana": "ｱｷﾀｼ",
        "address2_kana": "ｱﾗﾔｱｻﾋﾏﾁ",
        "prefecture_kanji": "秋田県",
        "address1_kanji": "秋田市",
        "address2_kanji": "新屋朝日町",
        "is_address2_has_multiple_postal_code": "0",
        "is_address2_has_multiple_sublocality": "0",
        "is_address2_includes_chome": "0",
        "is_postal_code_has_multiple_address2": "0",
        "updated_type": "0",
        "updated_reason_type": "0"
    },
    {
        "local_government_code": "05201",
        "postal_code_5digit": "01016",
        "postal_code_7digit": "0101614",
        "prefecture_kana": "ｱｷﾀｹﾝ",
        "address1_kana": "ｱｷﾀｼ",
        "address2_kana": "ｱﾗﾔﾜﾘﾔﾏﾏﾁ",
        "prefecture_kanji": "秋田県",
        "address1_kanji": "秋田市",
        "address2_kanji": "新屋割山町",
        "is_address2_has_multiple_postal_code": "0",
        "is_address2_has_multiple_sublocality": "0",
        "is_address2_includes_chome": "0",
        "is_postal_code_has_multiple_address2": "0",
        "updated_type": "0",
        "updated_reason_type": "0"
    },
    {
        "local_government_code": "05201",
        "postal_code_5digit": "01016",
        "postal_code_7digit": "0101615",
        "prefecture_kana": "ｱｷﾀｹﾝ",
        "address1_kana": "ｱｷﾀｼ",
        "address2_kana": "ｱﾗﾔﾌﾅﾊﾞﾏﾁ",
        "prefecture_kanji": "秋田県",
        "address1_kanji": "秋田市",
        "address2_kanji": "新屋船場町",
        "is_address2_has_multiple_postal_code": "0",
        "is_address2_has_multiple_sublocality": "0",
        "is_address2_includes_chome": "0",
        "is_postal_code_has_multiple_address2": "0",
        "updated_type": "0",
        "updated_reason_type": "0"
    },
    {
        "local_government_code": "05201",
        "postal_code_5digit": "01016",
        "postal_code_7digit": "0101616",
        "prefecture_kana": "ｱｷﾀｹﾝ",
        "address1_kana": "ｱｷﾀｼ",
        "address2_kana": "ｱﾗﾔﾏﾂﾐｶﾞｵｶﾐﾅﾐﾁｮｳ",
        "prefecture_kanji": "秋田県",
        "address1_kanji": "秋田市",
        "address2_kanji": "新屋松美ガ丘南町",
        "is_address2_has_multiple_postal_code": "0",
        "is_address2_has_multiple_sublocality": "0",
        "is_address2_includes_chome": "0",
        "is_postal_code_has_multiple_address2": "0",
        "updated_type": "0",
        "updated_reason_type": "0"
    },
    {
        "local_government_code": "05201",
        "postal_code_5digit": "01016",
        "postal_code_7digit": "0101617",
        "prefecture_kana": "ｱｷﾀｹﾝ",
        "address1_kana": "ｱｷﾀｼ",
        "address2_kana": "ｱﾗﾔﾏﾂﾐｶﾞｵｶﾋｶﾞｼﾁｮｳ",
        "prefecture_kanji": "秋田県",
        "address1_kanji": "秋田市",
        "address2_kanji": "新屋松美ガ丘東町",
        "is_address2_has_multiple_postal_code": "0",
        "is_address2_has_multiple_sublocality": "0",
        "is_address2_includes_chome": "0",
        "is_postal_code_has_multiple_address2": "0",
        "updated_type": "0",
        "updated_reason_type": "0"
    },
    {
        "local_government_code": "05201",
        "postal_code_5digit": "01016",
        "postal_code_7digit": "0101618",
        "prefecture_kana": "ｱｷﾀｹﾝ",
        "address1_kana": "ｱｷﾀｼ",
        "address2_kana": "ｱﾗﾔﾏﾂﾐｶﾞｵｶｷﾀﾁｮｳ",
        "prefecture_kanji": "秋田県",
        "address1_kanji": "秋田市",
        "address2_kanji": "新屋松美ガ丘北町",
        "is_address2_has_multiple_postal_code": "0",
        "is_address2_has_multiple_sublocality": "0",
        "is_address2_includes_chome": "0",
        "is_postal_code_has_multiple_address2": "0",
        "updated_type": "0",
        "updated_reason_type": "0"
    },
    {
        "local_government_code": "05201",
        "postal_code_5digit": "01016",
        "postal_code_7digit": "0101621",
        "prefecture_kana": "ｱｷﾀｹﾝ",
        "address1_kana": "ｱｷﾀｼ",
        "address2_kana": "ｱﾗﾔｸﾘﾀﾏﾁ",
        "prefecture_kanji": "秋田県",
        "address1_kanji": "秋田市",
        "address2_kanji": "新屋栗田町",
        "is_address2_has_multiple_postal_code": "0",
        "is_address2_has_multiple_sublocality": "0",
        "is_address2_includes_chome": "0",
        "is_postal_code_has_multiple_address2": "0",
        "updated_type": "0",
        "updated_reason_type": "0"
    },
    {
        "local_government_code": "05201",
        "postal_code_5digit": "01016",
        "postal_code_7digit": "0101622",
        "prefecture_kana": "ｱｷﾀｹﾝ",
        "address1_kana": "ｱｷﾀｼ",
        "address2_kana": "ｱﾗﾔﾋﾖｼﾏﾁ",
        "prefecture_kanji": "秋田県",
        "address1_kanji": "秋田市",
        "address2_kanji": "新屋日吉町",
        "is_address2_has_multiple_postal_code": "0",
        "is_address2_has_multiple_sublocality": "0",
        "is_address2_includes_chome": "0",
        "is_postal_code_has_multiple_address2": "0",
        "updated_type": "0",
        "updated_reason_type": "0"
    },
    {
        "local_government_code": "05201",
        "postal_code_5digit": "01016",
        "postal_code_7digit": "0101623",
        "prefecture_kana": "ｱｷﾀｹﾝ",
        "address1_kana": "ｱｷﾀｼ",
        "address2_kana": "ｱﾗﾔﾏﾁ",
        "prefecture_kanji": "秋田県",
        "address1_kanji": "秋田市",
        "address2_kanji": "新屋町",
        "is_address2_has_multiple_postal_code": "0",
        "is_address2_has_multiple_sublocality": "1",
        "is_address2_includes_chome": "0",
        "is_postal_code_has_multiple_address2": "0",
        "updated_type": "0",
        "updated_reason_type": "0"
    },
    {
        "local_government_code": "05201",
        "postal_code_5digit": "01016",
        "postal_code_7digit": "0101631",
        "prefecture_kana": "ｱｷﾀｹﾝ",
        "address1_kana": "ｱｷﾀｼ",
        "address2_kana": "ｱﾗﾔﾓﾄﾏﾁ",
        "prefecture_kanji": "秋田県",
        "address1_kanji": "秋田市",
        "address2_kanji": "新屋元町",
        "is_address2_has_multiple_postal_code": "0",
        "is_address2_has_multiple_sublocality": "0",
        "is_address2_includes_chome": "0",
        "is_postal_code_has_multiple_address2": "0",
        "updated_type": "0",
        "updated_reason_type": "0"
    },
    {
        "local_government_code": "05201",
        "postal_code_5digit": "01016",
        "postal_code_7digit": "0101632",
        "prefecture_kana": "ｱｷﾀｹﾝ",
        "address1_kana": "ｱｷﾀｼ",
        "address2_kana": "ｱﾗﾔｵｵｶﾜﾏﾁ",
        "prefecture_kanji": "秋田県",
        "address1_kanji": "秋田市",
        "address2_kanji": "新屋大川町",
        "is_address2_has_multiple_postal_code": "0",
        "is_address2_has_multiple_sublocality": "0",
        "is_address2_includes_chome": "0",
        "is_postal_code_has_multiple_address2": "0",
        "updated_type": "0",
        "updated_reason_type": "0"
    },
    {
        "local_government_code": "05201",
        "postal_code_5digit": "01016",
        "postal_code_7digit": "0101633",
        "prefecture_kana": "ｱｷﾀｹﾝ",
        "address1_kana": "ｱｷﾀｼ",
        "address2_kana": "ｱﾗﾔﾄﾘｷﾏﾁ",
        "prefecture_kanji": "秋田県",
        "address1_kanji": "秋田市",
        "address2_kanji": "新屋鳥木町",
        "is_address2_has_multiple_postal_code": "0",
        "is_address2_has_multiple_sublocality": "0",
        "is_address2_includes_chome": "0",
        "is_postal_code_has_multiple_address2": "0",
        "updated_type": "0",
        "updated_reason_type": "0"
    },
    {
        "local_government_code": "05201",
        "postal_code_5digit": "01016",
        "postal_code_7digit": "0101634",
        "prefecture_kana": "ｱｷﾀｹﾝ",
        "address1_kana": "ｱｷﾀｼ",
        "address2_kana": "ｱﾗﾔｵｷﾀﾏﾁ",
        "prefecture_kanji": "秋田県",
        "address1_kanji": "秋田市",
        "address2_kanji": "新屋沖田町",
        "is_address2_has_multiple_postal_code": "0",
        "is_address2_has_multiple_sublocality": "0",
        "is_address2_includes_chome": "0",
        "is_postal_code_has_multiple_address2": "0",
        "updated_type": "0",
        "updated_reason_type": "0"
    },
    {
        "local_government_code": "05201",
        "postal_code_5digit": "01016",
        "postal_code_7digit": "0101635",
        "prefecture_kana": "ｱｷﾀｹﾝ",
        "address1_kana": "ｱｷﾀｼ",
        "address2_kana": "ｱﾗﾔﾏｴﾉﾏﾁ",
        "prefecture_kanji": "秋田県",
        "address1_kanji": "秋田市",
        "address2_kanji": "新屋前野町",
        "is_address2_has_multiple_postal_code": "0",
        "is_address2_has_multiple_sublocality": "0",
        "is_address2_includes_chome": "0",
        "is_postal_code_has_multiple_address2": "0",
        "updated_type": "0",
        "updated_reason_type": "0"
    },
    {
        "local_government_code": "05201",
        "postal_code_5digit": "01016",
        "postal_code_7digit": "0101636",
        "prefecture_kana": "ｱｷﾀｹﾝ",
        "address1_kana": "ｱｷﾀｼ",
        "address2_kana": "ｱﾗﾔﾋﾅｲﾏﾁ",
        "prefecture_kanji": "秋田県",
        "address1_kanji": "秋田市",
        "address2_kanji": "新屋比内町",
        "is_address2_has_multiple_postal_code": "0",
        "is_address2_has_multiple_sublocality": "0",
        "is_address2_includes_chome": "0",
        "is_postal_code_has_multiple_address2": "0",
        "updated_type": "0",
        "updated_reason_type": "0"
    },
    {
        "local_government_code": "05201",
        "postal_code_5digit": "01016",
        "postal_code_7digit": "0101637",
        "prefecture_kana": "ｱｷﾀｹﾝ",
        "address1_kana": "ｱｷﾀｼ",
        "address2_kana": "ｱﾗﾔｵｵｷﾞﾏﾁ",
        "prefecture_kanji": "秋田県",
        "address1_kanji": "秋田市",
        "address2_kanji": "新屋扇町",
        "is_address2_has_multiple_postal_code": "0",
        "is_address2_has_multiple_sublocality": "0",
        "is_address2_includes_chome": "0",
        "is_postal_code_has_multiple_address2": "0",
        "updated_type": "0",
        "updated_reason_type": "0"
    },
    {
        "local_government_code": "05201",
        "postal_code_5digit": "01016",
        "postal_code_7digit": "0101638",
        "prefecture_kana": "ｱｷﾀｹﾝ",
        "address1_kana": "ｱｷﾀｼ",
        "address2_kana": "ｱﾗﾔｵﾓﾃﾏﾁ",
        "prefecture_kanji": "秋田県",
        "address1_kanji": "秋田市",
        "address2_kanji": "新屋表町",
        "is_address2_has_multiple_postal_code": "0",
        "is_address2_has_multiple_sublocality": "0",
        "is_address2_includes_chome": "0",
        "is_postal_code_has_multiple_address2": "0",
        "updated_type": "0",
        "updated_reason_type": "0"
    },
    {
        "local_government_code": "05201",
        "postal_code_5digit": "01016",
        "postal_code_7digit": "0101641",
        "prefecture_kana": "ｱｷﾀｹﾝ",
        "address1_kana": "ｱｷﾀｼ",
        "address2_kana": "ｱﾗﾔﾀｶﾐﾏﾁ",
        "prefecture_kanji": "秋田県",
        "address1_kanji": "秋田市",
        "address2_kanji": "新屋高美町",
        "is_address2_has_multiple_postal_code": "0",
        "is_address2_has_multiple_sublocality": "0",
        "is_address2_includes_chome": "0",
        "is_postal_code_has_multiple_address2": "0",
        "updated_type": "0",
        "updated_reason_type": "0"
    },
    {
        "local_government_code": "05201",
        "postal_code_5digit": "01016",
        "postal_code_7digit": "0101642",
        "prefecture_kana": "ｱｷﾀｹﾝ",
        "address1_kana": "ｱｷﾀｼ",
        "address2_kana": "ｱﾗﾔｼﾌﾞﾔﾏﾁ",
        "prefecture_kanji": "秋田県",
        "address1_kanji": "秋田市",
        "address2_kanji": "新屋渋谷町",
        "is_address2_has_multiple_postal_code": "0",
        "is_address2_has_multiple_sublocality": "0",
        "is_address2_includes_chome": "0",
        "is_postal_code_has_multiple_address2": "0",
        "updated_type": "0",
        "updated_reason_type": "0"
    },
    {
        "local_government_code": "05201",
        "postal_code_5digit": "01016",
        "postal_code_7digit": "0101643",
        "prefecture_kana": "ｱｷﾀｹﾝ",
        "address1_kana": "ｱｷﾀｼ",
        "address2_kana": "ｱﾗﾔﾀｼﾞﾘｻﾞﾜﾋｶﾞｼﾏﾁ",
        "prefecture_kanji": "秋田県",
        "address1_kanji": "秋田市",
        "address2_kanji": "新屋田尻沢東町",
        "is_address2_has_multiple_postal_code": "0",
        "is_address2_has_multiple_sublocality": "0",
        "is_address2_includes_chome": "0",
        "is_postal_code_has_multiple_address2": "0",
        "updated_type": "0",
        "updated_reason_type": "0"
    },
    {
        "local_government_code": "05201",
        "postal_code_5digit": "01016",
        "postal_code_7digit": "0101644",
        "prefecture_kana": "ｱｷﾀｹﾝ",
        "address1_kana": "ｱｷﾀｼ",
        "address2_kana": "ｱﾗﾔﾀｼﾞﾘｻﾞﾜﾅｶﾏﾁ",
        "prefecture_kanji": "秋田県",
        "address1_kanji": "秋田市",
        "address2_kanji": "新屋田尻沢中町",
        "is_address2_has_multiple_postal_code": "0",
        "is_address2_has_multiple_sublocality": "0",
        "is_address2_includes_chome": "0",
        "is_postal_code_has_multiple_address2": "0",
        "updated_type": "0",
        "updated_reason_type": "0"
    },
    {
        "local_government_code": "05201",
        "postal_code_5digit": "01016",
        "postal_code_7digit": "0101645",
        "prefecture_kana": "ｱｷﾀｹﾝ",
        "address1_kana": "ｱｷﾀｼ",
        "address2_kana": "ｱﾗﾔﾀｼﾞﾘｻﾞﾜﾆｼﾏﾁ",
        "prefecture_kanji": "秋田県",
        "address1_kanji": "秋田市",
        "address2_kanji": "新屋田尻沢西町",
        "is_address2_has_multiple_postal_code": "0",
        "is_address2_has_multiple_sublocality": "0",
        "is_address2_includes_chome": "0",
        "is_postal_code_has_multiple_address2": "0",
        "updated_type": "0",
        "updated_reason_type": "0"
    },
    {
        "local_government_code": "05201",
        "postal_code_5digit": "01016",
        "postal_code_7digit": "0101651",
        "prefecture_kana": "ｱｷﾀｹﾝ",
        "address1_kana": "ｱｷﾀｼ",
        "address2_kana": "ﾄﾖｲﾜｲｼﾀﾞｻﾞｶ",
        "prefecture_kanji": "秋田県",
        "address1_kanji": "秋田市",
        "address2_kanji": "豊岩石田坂",
        "is_address2_has_multiple_postal_code": "0",
        "is_address2_has_multiple_sublocality": "1",
        "is_address2_includes_chome": "0",
        "is_postal_code_has_multiple_address2": "0",
        "updated_type": "0",
        "updated_reason_type": "0"
    },
    {
        "local_government_code": "05201",
        "postal_code_5digit": "01016",
        "postal_code_7digit": "0101652",
        "prefecture_kana": "ｱｷﾀｹﾝ",
        "address1_kana": "ｱｷﾀｼ",
        "address2_kana": "ﾄﾖｲﾜﾄﾖﾏｷ",
        "prefecture_kanji": "秋田県",
        "address1_kanji": "秋田市",
        "address2_kanji": "豊岩豊巻",
        "is_address2_has_multiple_postal_code": "0",
        "is_address2_has_multiple_sublocality": "1",
        "is_address2_includes_chome": "0",
        "is_postal_code_has_multiple_address2": "0",
        "updated_type": "0",
        "updated_reason_type": "0"
    },
    {
        "local_government_code": "05201",
        "postal_code_5digit": "01016",
        "postal_code_7digit": "0101653",
        "prefecture_kana": "ｱｷﾀｹﾝ",
        "address1_kana": "ｱｷﾀｼ",
        "address2_kana": "ﾄﾖｲﾜｵﾔﾏ",
        "prefecture_kanji": "秋田県",
        "address1_kanji": "秋田市",
        "address2_kanji": "豊岩小山",
        "is_address2_has_multiple_postal_code": "0",
        "is_address2_has_multiple_sublocality": "1",
        "is_address2_includes_chome": "0",
        "is_postal_code_has_multiple_address2": "0",
        "updated_type": "0",
        "updated_reason_type": "0"
    },
    {
        "local_government_code": "05201",
        "postal_code_5digit": "01016",
        "postal_code_7digit": "0101654",
        "prefecture_kana": "ｱｷﾀｹﾝ",
        "address1_kana": "ｱｷﾀｼ",
        "address2_kana": "ﾊﾏﾀﾞ",
        "prefecture_kanji": "秋田県",
        "address1_kanji": "秋田市",
        "address2_kanji": "浜田",
        "is_address2_has_multiple_postal_code": "0",
        "is_address2_has_multiple_sublocality": "1",
        "is_address2_includes_chome": "0",
        "is_postal_code_has_multiple_address2": "0",
        "updated_type": "0",
        "updated_reason_type": "0"
    }
]