[
    {
        "local_government_code": "17210",
        "postal_code_5digit": "92902",
        "postal_code_7digit": "9290201",
        "prefecture_kana": "ｲｼｶﾜｹﾝ",
        "address1_kana": "ﾊｸｻﾝｼ",
        "address2_kana": "ｶｼﾏﾏﾁ",
        "prefecture_kanji": "石川県",
        "address1_kanji": "白山市",
        "address2_kanji": "鹿島町",
        "is_address2_has_multiple_postal_code": "0",
        "is_address2_has_multiple_sublocality": "0",
        "is_address2_includes_chome": "0",
        "is_postal_code_has_multiple_address2": "0",
        "updated_type": "0",
        "updated_reason_type": "0"
    },
    {
        "local_government_code": "17210",
        "postal_code_5digit": "92902",
        "postal_code_7digit": "9290202",
        "prefecture_kana": "ｲｼｶﾜｹﾝ",
        "address1_kana": "ﾊｸｻﾝｼ",
        "address2_kana": "ﾆｼﾖﾈﾐﾂﾏﾁ",
        "prefecture_kanji": "石川県",
        "address1_kanji": "白山市",
        "address2_kanji": "西米光町",
        "is_address2_has_multiple_postal_code": "0",
        "is_address2_has_multiple_sublocality": "0",
        "is_address2_includes_chome": "0",
        "is_postal_code_has_multiple_address2": "0",
        "updated_type": "0",
        "updated_reason_type": "0"
    },
    {
        "local_government_code": "17210",
        "postal_code_5digit": "92902",
        "postal_code_7digit": "9290203",
        "prefecture_kana": "ｲｼｶﾜｹﾝ",
        "address1_kana": "ﾊｸｻﾝｼ",
        "address2_kana": "ﾜｶｸｻﾏﾁ",
        "prefecture_kanji": "石川県",
        "address1_kanji": "白山市",
        "address2_kanji": "若草町",
        "is_address2_has_multiple_postal_code": "0",
        "is_address2_has_multiple_sublocality": "0",
        "is_address2_includes_chome": "0",
        "is_postal_code_has_multiple_address2": "0",
        "updated_type": "0",
        "updated_reason_type": "0"
    },
    {
        "local_government_code": "17210",
        "postal_code_5digit": "92902",
        "postal_code_7digit": "9290204",
        "prefecture_kana": "ｲｼｶﾜｹﾝ",
        "address1_kana": "ﾊｸｻﾝｼ",
        "address2_kana": "ﾋﾗｶﾏﾁ",
        "prefecture_kanji": "石川県",
        "address1_kanji": "白山市",
        "address2_kanji": "平加町",
        "is_address2_has_multiple_postal_code": "0",
        "is_address2_has_multiple_sublocality": "0",
        "is_address2_includes_chome": "0",
        "is_postal_code_has_multiple_address2": "0",
        "updated_type": "0",
        "updated_reason_type": "0"
    },
    {
        "local_government_code": "17210",
        "postal_code_5digit": "92902",
        "postal_code_7digit": "9290205",
        "prefecture_kana": "ｲｼｶﾜｹﾝ",
        "address1_kana": "ﾊｸｻﾝｼ",
        "address2_kana": "ﾊｽｲｹﾏﾁ",
        "prefecture_kanji": "石川県",
        "address1_kanji": "白山市",
        "address2_kanji": "蓮池町",
        "is_address2_has_multiple_postal_code": "0",
        "is_address2_has_multiple_sublocality": "0",
        "is_address2_includes_chome": "0",
        "is_postal_code_has_multiple_address2": "0",
        "updated_type": "0",
        "updated_reason_type": "0"
    },
    {
        "local_government_code": "17210",
        "postal_code_5digit": "92902",
        "postal_code_7digit": "9290206",
        "prefecture_kana": "ｲｼｶﾜｹﾝ",
        "address1_kana": "ﾊｸｻﾝｼ",
        "address2_kana": "ｶｼﾏﾀﾞｲﾗ",
        "prefecture_kanji": "石川県",
        "address1_kanji": "白山市",
        "address2_kanji": "鹿島平",
        "is_address2_has_multiple_postal_code": "0",
        "is_address2_has_multiple_sublocality": "0",
        "is_address2_includes_chome": "0",
        "is_postal_code_has_multiple_address2": "0",
        "updated_type": "0",
        "updated_reason_type": "0"
    },
    {
        "local_government_code": "17210",
        "postal_code_5digit": "92902",
        "postal_code_7digit": "9290211",
        "prefecture_kana": "ｲｼｶﾜｹﾝ",
        "address1_kana": "ﾊｸｻﾝｼ",
        "address2_kana": "ｲｾｷﾏﾁ",
        "prefecture_kanji": "石川県",
        "address1_kanji": "白山市",
        "address2_kanji": "井関町",
        "is_address2_has_multiple_postal_code": "0",
        "is_address2_has_multiple_sublocality": "0",
        "is_address2_includes_chome": "0",
        "is_postal_code_has_multiple_address2": "0",
        "updated_type": "0",
        "updated_reason_type": "0"
    },
    {
        "local_government_code": "17210",
        "postal_code_5digit": "92902",
        "postal_code_7digit": "9290212",
        "prefecture_kana": "ｲｼｶﾜｹﾝ",
        "address1_kana": "ﾊｸｻﾝｼ",
        "address2_kana": "ﾃﾄﾞﾘﾏﾁ",
        "prefecture_kanji": "石川県",
        "address1_kanji": "白山市",
        "address2_kanji": "手取町",
        "is_address2_has_multiple_postal_code": "0",
        "is_address2_has_multiple_sublocality": "0",
        "is_address2_includes_chome": "0",
        "is_postal_code_has_multiple_address2": "0",
        "updated_type": "0",
        "updated_reason_type": "0"
    },
    {
        "local_government_code": "17210",
        "postal_code_5digit": "92902",
        "postal_code_7digit": "9290213",
        "prefecture_kana": "ｲｼｶﾜｹﾝ",
        "address1_kana": "ﾊｸｻﾝｼ",
        "address2_kana": "ｽｴﾏｻﾏﾁ",
        "prefecture_kanji": "石川県",
        "address1_kanji": "白山市",
        "address2_kanji": "末正町",
        "is_address2_has_multiple_postal_code": "0",
        "is_address2_has_multiple_sublocality": "0",
        "is_address2_includes_chome": "0",
        "is_postal_code_has_multiple_address2": "0",
        "updated_type": "0",
        "updated_reason_type": "0"
    },
    {
        "local_government_code": "17210",
        "postal_code_5digit": "92902",
        "postal_code_7digit": "9290214",
        "prefecture_kana": "ｲｼｶﾜｹﾝ",
        "address1_kana": "ﾊｸｻﾝｼ",
        "address2_kana": "ﾁｮｳﾔﾏﾁ",
        "prefecture_kanji": "石川県",
        "address1_kanji": "白山市",
        "address2_kanji": "長屋町",
        "is_address2_has_multiple_postal_code": "0",
        "is_address2_has_multiple_sublocality": "0",
        "is_address2_includes_chome": "0",
        "is_postal_code_has_multiple_address2": "0",
        "updated_type": "0",
        "updated_reason_type": "0"
    },
    {
        "local_government_code": "17210",
        "postal_code_5digit": "92902",
        "postal_code_7digit": "9290215",
        "prefecture_kana": "ｲｼｶﾜｹﾝ",
        "address1_kana": "ﾊｸｻﾝｼ",
        "address2_kana": "ﾐｶﾜﾐﾅﾐﾏﾁ",
        "prefecture_kanji": "石川県",
        "address1_kanji": "白山市",
        "address2_kanji": "美川南町",
        "is_address2_has_multiple_postal_code": "0",
        "is_address2_has_multiple_sublocality": "0",
        "is_address2_includes_chome": "0",
        "is_postal_code_has_multiple_address2": "0",
        "updated_type": "0",
        "updated_reason_type": "0"
    },
    {
        "local_government_code": "17210",
        "postal_code_5digit": "92902",
        "postal_code_7digit": "9290216",
        "prefecture_kana": "ｲｼｶﾜｹﾝ",
        "address1_kana": "ﾊｸｻﾝｼ",
        "address2_kana": "ﾐｶﾜﾓﾄﾖｼﾏﾁ",
        "prefecture_kanji": "石川県",
        "address1_kanji": "白山市",
        "address2_kanji": "美川本吉町",
        "is_address2_has_multiple_postal_code": "0",
        "is_address2_has_multiple_sublocality": "0",
        "is_address2_includes_chome": "0",
        "is_postal_code_has_multiple_address2": "0",
        "updated_type": "0",
        "updated_reason_type": "0"
    },
    {
        "local_government_code": "17210",
        "postal_code_5digit": "92902",
        "postal_code_7digit": "9290217",
        "prefecture_kana": "ｲｼｶﾜｹﾝ",
        "address1_kana": "ﾊｸｻﾝｼ",
        "address2_kana": "ﾐﾅﾄﾏﾁ",
        "prefecture_kanji": "石川県",
        "address1_kanji": "白山市",
        "address2_kanji": "湊町",
        "is_address2_has_multiple_postal_code": "0",
        "is_address2_has_multiple_sublocality": "0",
        "is_address2_includes_chome": "0",
        "is_postal_code_has_multiple_address2": "0",
        "updated_type": "0",
        "updated_reason_type": "0"
    },
    {
        "local_government_code": "17210",
        "postal_code_5digit": "92902",
        "postal_code_7digit": "9290221",
        "prefecture_kana": "ｲｼｶﾜｹﾝ",
        "address1_kana": "ﾊｸｻﾝｼ",
        "address2_kana": "ﾐｶﾜｲﾏﾏﾁ",
        "prefecture_kanji": "石川県",
        "address1_kanji": "白山市",
        "address2_kanji": "美川今町",
        "is_address2_has_multiple_postal_code": "0",
        "is_address2_has_multiple_sublocality": "0",
        "is_address2_includes_chome": "0",
        "is_postal_code_has_multiple_address2": "0",
        "updated_type": "0",
        "updated_reason_type": "0"
    },
    {
        "local_government_code": "17210",
        "postal_code_5digit": "92902",
        "postal_code_7digit": "9290222",
        "prefecture_kana": "ｲｼｶﾜｹﾝ",
        "address1_kana": "ﾊｸｻﾝｼ",
        "address2_kana": "ﾐｶﾜｼﾝﾏﾁ",
        "prefecture_kanji": "石川県",
        "address1_kanji": "白山市",
        "address2_kanji": "美川新町",
        "is_address2_has_multiple_postal_code": "0",
        "is_address2_has_multiple_sublocality": "0",
        "is_address2_includes_chome": "0",
        "is_postal_code_has_multiple_address2": "0",
        "updated_type": "0",
        "updated_reason_type": "0"
    },
    {
        "local_government_code": "17210",
        "postal_code_5digit": "92902",
        "postal_code_7digit": "9290223",
        "prefecture_kana": "ｲｼｶﾜｹﾝ",
        "address1_kana": "ﾊｸｻﾝｼ",
        "address2_kana": "ﾐｶﾜｷﾀﾏﾁ",
        "prefecture_kanji": "石川県",
        "address1_kanji": "白山市",
        "address2_kanji": "美川北町",
        "is_address2_has_multiple_postal_code": "0",
        "is_address2_has_multiple_sublocality": "0",
        "is_address2_includes_chome": "0",
        "is_postal_code_has_multiple_address2": "0",
        "updated_type": "0",
        "updated_reason_type": "0"
    },
    {
        "local_government_code": "17210",
        "postal_code_5digit": "92902",
        "postal_code_7digit": "9290224",
        "prefecture_kana": "ｲｼｶﾜｹﾝ",
        "address1_kana": "ﾊｸｻﾝｼ",
        "address2_kana": "ﾐｶﾜﾅｶﾏﾁ",
        "prefecture_kanji": "石川県",
        "address1_kanji": "白山市",
        "address2_kanji": "美川中町",
        "is_address2_has_multiple_postal_code": "0",
        "is_address2_has_multiple_sublocality": "0",
        "is_address2_includes_chome": "0",
        "is_postal_code_has_multiple_address2": "0",
        "updated_type": "0",
        "updated_reason_type": "0"
    },
    {
        "local_government_code": "17210",
        "postal_code_5digit": "92902",
        "postal_code_7digit": "9290231",
        "prefecture_kana": "ｲｼｶﾜｹﾝ",
        "address1_kana": "ﾊｸｻﾝｼ",
        "address2_kana": "ﾐｶﾜﾜﾅﾐﾏﾁ",
        "prefecture_kanji": "石川県",
        "address1_kanji": "白山市",
        "address2_kanji": "美川和波町",
        "is_address2_has_multiple_postal_code": "0",
        "is_address2_has_multiple_sublocality": "0",
        "is_address2_includes_chome": "0",
        "is_postal_code_has_multiple_address2": "0",
        "updated_type": "0",
        "updated_reason_type": "0"
    },
    {
        "local_government_code": "17210",
        "postal_code_5digit": "92902",
        "postal_code_7digit": "9290232",
        "prefecture_kana": "ｲｼｶﾜｹﾝ",
        "address1_kana": "ﾊｸｻﾝｼ",
        "address2_kana": "ﾐｶﾜｽｴﾋﾛﾏﾁ",
        "prefecture_kanji": "石川県",
        "address1_kanji": "白山市",
        "address2_kanji": "美川末広町",
        "is_address2_has_multiple_postal_code": "0",
        "is_address2_has_multiple_sublocality": "0",
        "is_address2_includes_chome": "0",
        "is_postal_code_has_multiple_address2": "0",
        "updated_type": "0",
        "updated_reason_type": "0"
    },
    {
        "local_government_code": "17210",
        "postal_code_5digit": "92902",
        "postal_code_7digit": "9290233",
        "prefecture_kana": "ｲｼｶﾜｹﾝ",
        "address1_kana": "ﾊｸｻﾝｼ",
        "address2_kana": "ﾐｶﾜﾊﾏﾏﾁ",
        "prefecture_kanji": "石川県",
        "address1_kanji": "白山市",
        "address2_kanji": "美川浜町",
        "is_address2_has_multiple_postal_code": "0",
        "is_address2_has_multiple_sublocality": "0",
        "is_address2_includes_chome": "0",
        "is_postal_code_has_multiple_address2": "0",
        "updated_type": "0",
        "updated_reason_type": "0"
    },
    {
        "local_government_code": "17210",
        "postal_code_5digit": "92902",
        "postal_code_7digit": "9290234",
        "prefecture_kana": "ｲｼｶﾜｹﾝ",
        "address1_kana": "ﾊｸｻﾝｼ",
        "address2_kana": "ﾐｶﾜｼﾞﾝｺｳﾏﾁ",
        "prefecture_kanji": "石川県",
        "address1_kanji": "白山市",
        "address2_kanji": "美川神幸町",
        "is_address2_has_multiple_postal_code": "0",
        "is_address2_has_multiple_sublocality": "0",
        "is_address2_includes_chome": "0",
        "is_postal_code_has_multiple_address2": "0",
        "updated_type": "0",
        "updated_reason_type": "0"
    },
    {
        "local_government_code": "17210",
        "postal_code_5digit": "92902",
        "postal_code_7digit": "9290235",
        "prefecture_kana": "ｲｼｶﾜｹﾝ",
        "address1_kana": "ﾊｸｻﾝｼ",
        "address2_kana": "ﾐｶﾜｴｲﾀｲﾏﾁ",
        "prefecture_kanji": "石川県",
        "address1_kanji": "白山市",
        "address2_kanji": "美川永代町",
        "is_address2_has_multiple_postal_code": "0",
        "is_address2_has_multiple_sublocality": "0",
        "is_address2_includes_chome": "0",
        "is_postal_code_has_multiple_address2": "0",
        "updated_type": "0",
        "updated_reason_type": "0"
    }
]