[
    {
        "code": "08231",
        "postal_old": "30914",
        "postal_new": "3091451",
        "pref_kana": "ｲﾊﾞﾗｷｹﾝ",
        "address1_kana": "ｻｸﾗｶﾞﾜｼ",
        "address2_kana": "ﾆｼｺﾊﾞﾅﾜ",
        "pref": "茨城県",
        "address1": "桜川市",
        "address2": "西小塙",
        "is_multi_code": "0",
        "is_koaza": "0",
        "is_choume": "0",
        "is_multi_place": "0",
        "is_updated": "0",
        "update_reason": "0"
    },
    {
        "code": "08231",
        "postal_old": "30914",
        "postal_new": "3091452",
        "pref_kana": "ｲﾊﾞﾗｷｹﾝ",
        "address1_kana": "ｻｸﾗｶﾞﾜｼ",
        "address2_kana": "ｶﾓﾍﾞ",
        "pref": "茨城県",
        "address1": "桜川市",
        "address2": "加茂部",
        "is_multi_code": "0",
        "is_koaza": "0",
        "is_choume": "0",
        "is_multi_place": "0",
        "is_updated": "0",
        "update_reason": "0"
    },
    {
        "code": "08231",
        "postal_old": "30914",
        "postal_new": "3091453",
        "pref_kana": "ｲﾊﾞﾗｷｹﾝ",
        "address1_kana": "ｻｸﾗｶﾞﾜｼ",
        "address2_kana": "ﾄﾓﾍﾞ",
        "pref": "茨城県",
        "address1": "桜川市",
        "address2": "友部",
        "is_multi_code": "0",
        "is_koaza": "0",
        "is_choume": "0",
        "is_multi_place": "0",
        "is_updated": "0",
        "update_reason": "0"
    },
    {
        "code": "08231",
        "postal_old": "30914",
        "postal_new": "3091454",
        "pref_kana": "ｲﾊﾞﾗｷｹﾝ",
        "address1_kana": "ｻｸﾗｶﾞﾜｼ",
        "address2_kana": "ｶﾐｼﾛ",
        "pref": "茨城県",
        "address1": "桜川市",
        "address2": "上城",
        "is_multi_code": "0",
        "is_koaza": "0",
        "is_choume": "0",
        "is_multi_place": "0",
        "is_updated": "0",
        "update_reason": "0"
    },
    {
        "code": "08231",
        "postal_old": "30914",
        "postal_new": "3091455",
        "pref_kana": "ｲﾊﾞﾗｷｹﾝ",
        "address1_kana": "ｻｸﾗｶﾞﾜｼ",
        "address2_kana": "ﾐﾄ",
        "pref": "茨城県",
        "address1": "桜川市",
        "address2": "水戸",
        "is_multi_code": "0",
        "is_koaza": "0",
        "is_choume": "0",
        "is_multi_place": "0",
        "is_updated": "0",
        "update_reason": "0"
    },
    {
        "code": "08231",
        "postal_old": "30914",
        "postal_new": "3091456",
        "pref_kana": "ｲﾊﾞﾗｷｹﾝ",
        "address1_kana": "ｻｸﾗｶﾞﾜｼ",
        "address2_kana": "ｱｵﾔｷﾞ",
        "pref": "茨城県",
        "address1": "桜川市",
        "address2": "青柳",
        "is_multi_code": "0",
        "is_koaza": "0",
        "is_choume": "0",
        "is_multi_place": "0",
        "is_updated": "0",
        "update_reason": "0"
    },
    {
        "code": "08231",
        "postal_old": "30914",
        "postal_new": "3091457",
        "pref_kana": "ｲﾊﾞﾗｷｹﾝ",
        "address1_kana": "ｻｸﾗｶﾞﾜｼ",
        "address2_kana": "ｲｿﾍﾞ",
        "pref": "茨城県",
        "address1": "桜川市",
        "address2": "磯部",
        "is_multi_code": "0",
        "is_koaza": "0",
        "is_choume": "0",
        "is_multi_place": "0",
        "is_updated": "0",
        "update_reason": "0"
    },
    {
        "code": "08231",
        "postal_old": "30914",
        "postal_new": "3091458",
        "pref_kana": "ｲﾊﾞﾗｷｹﾝ",
        "address1_kana": "ｻｸﾗｶﾞﾜｼ",
        "address2_kana": "ｲﾅ",
        "pref": "茨城県",
        "address1": "桜川市",
        "address2": "稲",
        "is_multi_code": "0",
        "is_koaza": "0",
        "is_choume": "0",
        "is_multi_place": "0",
        "is_updated": "0",
        "update_reason": "0"
    },
    {
        "code": "08231",
        "postal_old": "30914",
        "postal_new": "3091461",
        "pref_kana": "ｲﾊﾞﾗｷｹﾝ",
        "address1_kana": "ｻｸﾗｶﾞﾜｼ",
        "address2_kana": "ﾏﾂﾀﾞ",
        "pref": "茨城県",
        "address1": "桜川市",
        "address2": "松田",
        "is_multi_code": "0",
        "is_koaza": "0",
        "is_choume": "0",
        "is_multi_place": "0",
        "is_updated": "0",
        "update_reason": "0"
    },
    {
        "code": "08231",
        "postal_old": "30914",
        "postal_new": "3091462",
        "pref_kana": "ｲﾊﾞﾗｷｹﾝ",
        "address1_kana": "ｻｸﾗｶﾞﾜｼ",
        "address2_kana": "ｿﾈ",
        "pref": "茨城県",
        "address1": "桜川市",
        "address2": "曽根",
        "is_multi_code": "0",
        "is_koaza": "0",
        "is_choume": "0",
        "is_multi_place": "0",
        "is_updated": "0",
        "update_reason": "0"
    },
    {
        "code": "08231",
        "postal_old": "30914",
        "postal_new": "3091463",
        "pref_kana": "ｲﾊﾞﾗｷｹﾝ",
        "address1_kana": "ｻｸﾗｶﾞﾜｼ",
        "address2_kana": "ﾀｶﾊﾀ",
        "pref": "茨城県",
        "address1": "桜川市",
        "address2": "高幡",
        "is_multi_code": "0",
        "is_koaza": "0",
        "is_choume": "0",
        "is_multi_place": "0",
        "is_updated": "0",
        "update_reason": "0"
    },
    {
        "code": "08231",
        "postal_old": "30914",
        "postal_new": "3091464",
        "pref_kana": "ｲﾊﾞﾗｷｹﾝ",
        "address1_kana": "ｻｸﾗｶﾞﾜｼ",
        "address2_kana": "ｲﾏｲｽﾞﾐ",
        "pref": "茨城県",
        "address1": "桜川市",
        "address2": "今泉",
        "is_multi_code": "0",
        "is_koaza": "0",
        "is_choume": "0",
        "is_multi_place": "0",
        "is_updated": "0",
        "update_reason": "0"
    },
    {
        "code": "08231",
        "postal_old": "30914",
        "postal_new": "3091465",
        "pref_kana": "ｲﾊﾞﾗｷｹﾝ",
        "address1_kana": "ｻｸﾗｶﾞﾜｼ",
        "address2_kana": "ｷｳｴ",
        "pref": "茨城県",
        "address1": "桜川市",
        "address2": "木植",
        "is_multi_code": "0",
        "is_koaza": "0",
        "is_choume": "0",
        "is_multi_place": "0",
        "is_updated": "0",
        "update_reason": "0"
    },
    {
        "code": "08231",
        "postal_old": "30914",
        "postal_new": "3091466",
        "pref_kana": "ｲﾊﾞﾗｷｹﾝ",
        "address1_kana": "ｻｸﾗｶﾞﾜｼ",
        "address2_kana": "ｻﾙﾀﾞ",
        "pref": "茨城県",
        "address1": "桜川市",
        "address2": "猿田",
        "is_multi_code": "0",
        "is_koaza": "0",
        "is_choume": "0",
        "is_multi_place": "0",
        "is_updated": "0",
        "update_reason": "0"
    }
]