[
    {
        "code": "20521",
        "postal_old": "38906",
        "postal_new": "3890600",
        "pref_kana": "ﾅｶﾞﾉｹﾝ",
        "address1_kana": "ﾊﾆｼﾅｸﾞﾝｻｶｷﾏﾁ",
        "address2_kana": "ｲｶﾆｹｲｻｲｶﾞﾅｲﾊﾞｱｲ",
        "pref": "長野県",
        "address1": "埴科郡坂城町",
        "address2": "以下に掲載がない場合",
        "is_multi_code": "0",
        "is_koaza": "0",
        "is_choume": "0",
        "is_multi_place": "0",
        "is_updated": "0",
        "update_reason": "0"
    },
    {
        "code": "20521",
        "postal_old": "38906",
        "postal_new": "3890601",
        "pref_kana": "ﾅｶﾞﾉｹﾝ",
        "address1_kana": "ﾊﾆｼﾅｸﾞﾝｻｶｷﾏﾁ",
        "address2_kana": "ｻｶｷ",
        "pref": "長野県",
        "address1": "埴科郡坂城町",
        "address2": "坂城",
        "is_multi_code": "0",
        "is_koaza": "0",
        "is_choume": "0",
        "is_multi_place": "0",
        "is_updated": "0",
        "update_reason": "0"
    },
    {
        "code": "20521",
        "postal_old": "38906",
        "postal_new": "3890602",
        "pref_kana": "ﾅｶﾞﾉｹﾝ",
        "address1_kana": "ﾊﾆｼﾅｸﾞﾝｻｶｷﾏﾁ",
        "address2_kana": "ﾅｶﾉｼﾞｮｳ",
        "pref": "長野県",
        "address1": "埴科郡坂城町",
        "address2": "中之条",
        "is_multi_code": "0",
        "is_koaza": "0",
        "is_choume": "0",
        "is_multi_place": "0",
        "is_updated": "0",
        "update_reason": "0"
    },
    {
        "code": "20521",
        "postal_old": "38906",
        "postal_new": "3890603",
        "pref_kana": "ﾅｶﾞﾉｹﾝ",
        "address1_kana": "ﾊﾆｼﾅｸﾞﾝｻｶｷﾏﾁ",
        "address2_kana": "ﾐﾅﾐｼﾞｮｳ",
        "pref": "長野県",
        "address1": "埴科郡坂城町",
        "address2": "南条",
        "is_multi_code": "0",
        "is_koaza": "0",
        "is_choume": "0",
        "is_multi_place": "0",
        "is_updated": "0",
        "update_reason": "0"
    },
    {
        "code": "20521",
        "postal_old": "38906",
        "postal_new": "3890604",
        "pref_kana": "ﾅｶﾞﾉｹﾝ",
        "address1_kana": "ﾊﾆｼﾅｸﾞﾝｻｶｷﾏﾁ",
        "address2_kana": "ｱﾐｶｹ",
        "pref": "長野県",
        "address1": "埴科郡坂城町",
        "address2": "網掛",
        "is_multi_code": "0",
        "is_koaza": "0",
        "is_choume": "0",
        "is_multi_place": "0",
        "is_updated": "0",
        "update_reason": "0"
    },
    {
        "code": "20521",
        "postal_old": "38906",
        "postal_new": "3890605",
        "pref_kana": "ﾅｶﾞﾉｹﾝ",
        "address1_kana": "ﾊﾆｼﾅｸﾞﾝｻｶｷﾏﾁ",
        "address2_kana": "ｳﾜﾀﾞｲﾗ",
        "pref": "長野県",
        "address1": "埴科郡坂城町",
        "address2": "上平",
        "is_multi_code": "0",
        "is_koaza": "0",
        "is_choume": "0",
        "is_multi_place": "0",
        "is_updated": "0",
        "update_reason": "0"
    },
    {
        "code": "20521",
        "postal_old": "38906",
        "postal_new": "3890606",
        "pref_kana": "ﾅｶﾞﾉｹﾝ",
        "address1_kana": "ﾊﾆｼﾅｸﾞﾝｻｶｷﾏﾁ",
        "address2_kana": "ｶﾐｺﾞﾐｮｳ",
        "pref": "長野県",
        "address1": "埴科郡坂城町",
        "address2": "上五明",
        "is_multi_code": "0",
        "is_koaza": "0",
        "is_choume": "0",
        "is_multi_place": "0",
        "is_updated": "0",
        "update_reason": "0"
    }
]